MANIFEST.in
README.md
requirements.txt
setup.py
cront/__init__.py
cront.egg-info/PKG-INFO
cront.egg-info/SOURCES.txt
cront.egg-info/dependency_links.txt
cront.egg-info/not-zip-safe
cront.egg-info/requires.txt
cront.egg-info/top_level.txt
tests/__init__.py