Metadata-Version: 1.1
Name: cront
Version: 0.1.0
Summary: cront is a library that can make the task apps like crontab.
Home-page: https://github.com/asmodius/cront
Author: Asmodius
Author-email: asmodius.a@gmail.com
License: MIT
Download-URL: https://github.com/asmodius/cront/archive/master.zip
Keywords: tornado crontab
Platform: UNKNOWN
Classifier: Development Status :: 4 - Beta
Classifier: License :: OSI Approved :: MIT License
Classifier: Intended Audience :: Developers
Classifier: License :: OSI Approved
Classifier: Programming Language :: Python :: 2.7
Classifier: Programming Language :: Python :: 3.5
Classifier: Programming Language :: Python :: 3.6
Classifier: Topic :: Software Development :: Libraries :: Application Frameworks
